[
	{ "text": "1 Schools and studies", "link": "1-schools" },
	{ "text": "2 Clothing and fashion", "link": "2-clothing" },
	{ "text": "3 Travelling", "link": "3-travelling" },
	{ "text": "4 Housing", "link": "4-housing" },
	{ "text": "5 People in the modern world", "link": "5-people" },
	{ "text": "6 Jobs and future plans", "link": "6-jobs" },
	{ "text": "7 Ways of spending holidays", "link": "7-holidays" },
	{ "text": "8 Other English speaking countries", "link": "8-english-speaking-countries" },
	{ "text": "9 Mass media", "link": "9-media" },
	{ "text": "10 The Czech Republic", "link": "10-czechia" },
	{ "text": "11 The USA", "link": "11-usa" },
	{ "text": "12 Important international organisations", "link": "12-organisations" },
	{ "text": "13 Festivals and holidays", "link": "13-festivals" },
	{ "text": "14 Opinions of my hometown", "link": "14-hometown" },
	{ "text": "15 Stereotypes and etiquette", "link": "15-stereotypes" },
	{ "text": "16 Entertainment", "link": "16-entertainment" },
	{ "text": "17 Shopping and advertising", "link": "17-shopping" },
	{ "text": "18 Weather and natural disasters", "link": "18-weather" },
	{ "text": "19 Nature and environment", "link": "19-environment" },
	{ "text": "20 Outstanding personality", "link": "20-personality" },
	{ "text": "21 The human body and health", "link": "21-health" },
	{ "text": "22 Food and eating habits", "link": "22-food" },
	{ "text": "23 Family, daily routine, leisure time and hobbies", "link": "23-family" },
	{ "text": "24 Sports and games", "link": "24-sports" },
	{ "text": "25 The United Kingdom", "link": "25-uk" }
]
